model_manage_client/__init__.py
model_manage_client/client.py
model_manage_client/test.py
model_manage_client-0.0.1.8.dist-info/licenses/LICENSE
model_manage_client-0.0.1.8.dist-info/METADATA
model_manage_client-0.0.1.8.dist-info/WHEEL
model_manage_client-0.0.1.8.dist-info/top_level.txt
model_manage_client-0.0.1.8.dist-info/RECORD
