Metadata-Version: 2.4
Name: model-manage-client
Version: 0.0.1.8
Summary: A package for interacting with the Model management Service-API
Home-page: https://github.com/model-management
Author: Model-Manager
Author-email: hello@advantech.ai
License: MIT
Keywords: model management nlp ai language-processing
Classifier: Programming Language :: Python :: 3
Classifier: License :: OSI Approved :: MIT License
Classifier: Operating System :: OS Independent
Requires-Python: >=3.6
License-File: LICENSE
Requires-Dist: requests
Dynamic: author
Dynamic: author-email
Dynamic: classifier
Dynamic: description
Dynamic: description-content-type
Dynamic: home-page
Dynamic: keywords
Dynamic: license
Dynamic: license-file
Dynamic: requires-dist
Dynamic: requires-python
Dynamic: summary
